filegpt/FileGPT.py
filegpt/__init__.py
filegpt/openai_wrapper.py
filegpt/personalities.py
filegpt-0.1.8.dist-info/METADATA
filegpt-0.1.8.dist-info/WHEEL
filegpt-0.1.8.dist-info/entry_points.txt
filegpt-0.1.8.dist-info/top_level.txt
filegpt-0.1.8.dist-info/RECORD
