Metadata-Version: 2.1
Name: filegpt
Version: 0.1.8
Summary: A tool for autocompleting text files using OpenAI's GPT models.
Home-page: https://github.com/bachittle/FileGPT
Author: Bailey Chittle
Author-email: bachittle@gmail.com
Classifier: Programming Language :: Python :: 3
Classifier: License :: OSI Approved :: MIT License
Classifier: Operating System :: OS Independent
Requires-Dist: openai
Requires-Dist: tiktoken
